README.txt
check_airos_version.py
ez_setup.py
setup.py
guifi_nagios.egg-info/PKG-INFO
guifi_nagios.egg-info/SOURCES.txt
guifi_nagios.egg-info/dependency_links.txt
guifi_nagios.egg-info/not-zip-safe
guifi_nagios.egg-info/requires.txt
guifi_nagios.egg-info/top_level.txt