Metadata-Version: 1.0
Name: guifi-nagios
Version: 0.1
Summary: Nagios helpers for guifi.net networks
Home-page: http://lagunak.gisa-elkartea.org/projects/guifinagios/
Author: Ales Zabala Alava (Shagi)
Author-email: shagi@gisa-elkartea.org
License: GPLv3+
Platform: UNKNOWN
